README.md
log.yaml
service/__init__.py
service/__main__.py
service/_builder.py
service/_config.py
service/_sentry.py
service/ext/__init__.py
service/ext/api.py
service/ext/rpc.py
service/fn.py
service/i18n.py
service/log/__init__.py
service/log/formatter.py
service/log/logger.py
service/log/term.py
service/testing.py
tests/__init__.py
tests/conftest.py
tests/test_config.py
tests/test_fn.py
tests/test_i18n.py
tests/test_logger.py
pbt_service-5.0.0.dist-info/WHEEL
pbt_service-5.0.0.dist-info/METADATA
pbt_service-5.0.0.dist-info/RECORD
