Metadata-Version: 2.1
Name: pbt-service
Version: 5.0.0
Summary: PortalBilet service core
Author: everhide
Author-email: i.tolkachnikov@gmail.com
Requires-Python: >=3.9,<4.0
Classifier: Programming Language :: Python :: 3
Classifier: Programming Language :: Python :: 3.10
Classifier: Programming Language :: Python :: 3.9
Requires-Dist: Babel (==2.10.1)
Requires-Dist: Faker (>=13.11.1,<14.0.0)
Requires-Dist: PyYAML (>=6.0,<7.0)
Requires-Dist: Pygments (>=2.12.0,<3.0.0)
Requires-Dist: fastapi (>=0.78.0,<0.79.0)
Requires-Dist: fire (>=0.4.0,<0.5.0)
Requires-Dist: httpx (==0.22.0)
Requires-Dist: jsonrpcserver (>=5.0.7,<6.0.0)
Requires-Dist: logging-json (>=0.2.1,<0.3.0)
Requires-Dist: pytest (>=7.1.2,<8.0.0)
Requires-Dist: pytest-asyncio (==0.18.3)
Requires-Dist: pytest-logger (>=0.5.1,<0.6.0)
Requires-Dist: python-dotenv (>=0.20.0,<0.21.0)
Requires-Dist: requests (>=2.27.1,<3.0.0)
Requires-Dist: sentry-sdk (==1.5.10)
Requires-Dist: tblib (>=1.7.0,<2.0.0)
Requires-Dist: toml (==0.10.2)
Requires-Dist: uvicorn (>=0.17.6,<0.18.0)
Requires-Dist: yarl (>=1.7.2,<2.0.0)
